task2/f1_fsm.sv
module f1_fsm #(
    parameter DATA_WIDTH = 8
) (
    input logic rst, 
    input logic en,
    input logic clk,
    output logic [DATA_WIDTH-1:0] data_out
);

    // define states
    typedef enum {S0, S1, S2, S3, S4, S5, S6, S7, S8} state;
    state current_state, next_state;

    always_ff @(posedge clk) begin
        if (rst) current_state <= S0;
        else current_state <= next_state;
    end

    // next state logic
    always_comb 
        case (current_state)
            S0 : if(en) next_state = S1; else next_state = current_state;
            S1 : if(en) next_state = S2; else next_state = current_state;
            S2 : if(en) next_state = S3; else next_state = current_state;
            S3 : if(en) next_state = S4; else next_state = current_state;
            S4 : if(en) next_state = S5; else next_state = current_state;
            S5 : if(en) next_state = S6; else next_state = current_state;
            S6 : if(en) next_state = S7; else next_state = current_state;
            S7 : if(en) next_state = S8; else next_state = current_state;
            S8 : if(en) next_state = S0; else next_state = current_state;
            default: next_state = S0; 
        endcase

    // output logic
    always_comb 
        case (current_state)
            S0 : data_out = 8'b0;
            S1 : data_out = 8'b1;
            S2 : data_out = 8'b11;
            S3 : data_out = 8'b111;
            S4 : data_out = 8'b1111;
            S5 : data_out = 8'b11111;
            S6 : data_out = 8'b111111;
            S7 : data_out = 8'b1111111; 
            S8 : data_out = 8'b11111111;
            default: data_out = 8'b0; 
        endcase
    
endmodule

task2/f1_fsm.vcd
$version Generated by VerilatedVcd $end
$date Thu Nov  2 11:04:38 2023 $end
$timescale 1ps $end

 $scope module TOP $end
  $var wire  1 % clk $end
  $var wire  8 & data_out [7:0] $end
  $var wire  1 $ en $end
  $var wire  1 # rst $end
  $scope module f1_fsm $end
   $var wire 32 ) DATA_WIDTH [31:0] $end
   $var wire  1 % clk $end
   $var wire 32 ' current_state [31:0] $end
   $var wire  8 & data_out [7:0] $end
   $var wire  1 $ en $end
   $var wire 32 ( next_state [31:0] $end
   $var wire  1 # rst $end
  $upscope $end
 $upscope $end
$enddefinitions $end


#0
1#
1$
0%
b00000000 &
b00000000000000000000000000000000 '
b00000000000000000000000000000000 (
b00000000000000000000000000001000 )
#1
1%
b00000000000000000000000000000001 (
#2
0$
0%
#3
1%
b00000000000000000000000000000000 (
#4
0%
#5
1%
#6
0#
0%
#7
1%
#8
0%
#9
1%
#10
0%
#11
1%
#12
0%
#13
1%
#14
0%
#15
1%
#16
0%
#17
1%
#18
0%
#19
1%
#20
0%
#21
1%
#22
0%
#23
1%
#24
0%
#25
1%
#26
0%
#27
1%
#28
0%
#29
1%
#30
0%
#31
1%
#32
0%
#33
1%
#34
0%
#35
1%
#36
0%
#37
1%
#38
0%
#39
1%
#40
0%
#41
1%
#42
0%
#43
1%
#44
0%
#45
1%
#46
0%
#47
1%
#48
0%
#49
1%
#50
0%
#51
1%
#52
0%
#53
1%
#54
0%
#55
1%
#56
0%
#57
1%
#58
0%
#59
1%
#60
0%
#61
1%
#62
0%
#63
1%
#64
0%
#65
1%
#66
0%
#67
1%
#68
0%
#69
1%
#70
0%
#71
1%
#72
0%
#73
1%
#74
0%
#75
1%
#76
0%
#77
1%
#78
0%
#79
1%
#80
0%
#81
1%
#82
0%
#83
1%
#84
1$
0%
#85
1%
b00000000000000000000000000000001 (
#86
0$
0%
b00000001 &
b00000000000000000000000000000001 '
b00000000000000000000000000000010 (
#87
1%
b00000000000000000000000000000001 (
#88
0%
#89
1%
#90
0%
#91
1%
#92
0%
#93
1%
#94
0%
#95
1%
#96
0%
#97
1%
#98
0%
#99
1%
#100
0%
#101
1%
#102
0%
#103
1%
#104
0%
#105
1%
#106
0%
#107
1%
#108
0%
#109
1%
#110
1$
0%
#111
1%
b00000000000000000000000000000010 (
#112
0$
0%
b00000011 &
b00000000000000000000000000000010 '
b00000000000000000000000000000011 (
#113
1%
b00000000000000000000000000000010 (
#114
0%
#115
1%
#116
0%
#117
1%
#118
0%
#119
1%
#120
0%
#121
1%
#122
0%
#123
1%
#124
0%
#125
1%
#126
0%
#127
1%
#128
0%
#129
1%
#130
0%
#131
1%
#132
0%
#133
1%
#134
0%
#135
1%
#136
0%
#137
1%
#138
0%
#139
1%
#140
0%
#141
1%
#142
0%
#143
1%
#144
0%
#145
1%
#146
0%
#147
1%
#148
0%
#149
1%
#150
0%
#151
1%
#152
0%
#153
1%
#154
1$
0%
#155
1%
b00000000000000000000000000000011 (
#156
0$
0%
b00000111 &
b00000000000000000000000000000011 '
b00000000000000000000000000000100 (
#157
1%
b00000000000000000000000000000011 (
#158
0%
#159
1%
#160
0%
#161
1%
#162
0%
#163
1%
#164
0%
#165
1%
#166
0%
#167
1%
#168
0%
#169
1%
#170
0%
#171
1%
#172
0%
#173
1%
#174
0%
#175
1%
#176
0%
#177
1%
#178
0%
#179
1%
#180
1$
0%
#181
1%
b00000000000000000000000000000100 (
#182
0$
0%
b00001111 &
b00000000000000000000000000000100 '
b00000000000000000000000000000101 (
#183
1%
b00000000000000000000000000000100 (
#184
0%
#185
1%
#186
0%
#187
1%
#188
0%
#189
1%
#190
0%
#191
1%
#192
0%
#193
1%
#194
0%
#195
1%
#196
0%
#197
1%
#198
0%
#199
1%
#200
0%
#201
1%
#202
0%
#203
1%
#204
0%
#205
1%
#206
1$
0%
#207
1%
b00000000000000000000000000000101 (
#208
0$
0%
b00011111 &
b00000000000000000000000000000101 '
b00000000000000000000000000000110 (
#209
1%
b00000000000000000000000000000101 (
#210
0%
#211
1%
#212
0%
#213
1%
#214
0%
#215
1%
#216
0%
#217
1%
#218
0%
#219
1%
#220
0%
#221
1%
#222
0%
#223
1%
#224
0%
#225
1%
#226
0%
#227
1%
#228
0%
#229
1%
#230
1$
0%
#231
1%
b00000000000000000000000000000110 (
#232
0$
0%
b00111111 &
b00000000000000000000000000000110 '
b00000000000000000000000000000111 (
#233
1%
b00000000000000000000000000000110 (
#234
0%
#235
1%
#236
0%
#237
1%
#238
0%
#239
1%
#240
0%
#241
1%
#242
0%
#243
1%
#244
0%
#245
1%
#246
0%
#247
1%
#248
0%
#249
1%
#250
0%
#251
1%
#252
0%
#253
1%
#254
0%
#255
1%
#256
1$
0%
#257
1%
b00000000000000000000000000000111 (
#258
0$
0%
b01111111 &
b00000000000000000000000000000111 '
b00000000000000000000000000001000 (
#259
1%
b00000000000000000000000000000111 (
#260
0%
#261
1%
#262
0%
#263
1%
#264
0%
#265
1%
#266
0%
#267
1%
#268
0%
#269
1%
#270
0%
#271
1%
#272
0%
#273
1%
#274
0%
#275
1%
#276
0%
#277
1%
#278
1$
0%
#279
1%
b00000000000000000000000000001000 (
#280
0$
0%
b11111111 &
b00000000000000000000000000001000 '
b00000000000000000000000000000000 (
#281
1%
b00000000000000000000000000001000 (
#282
0%
#283
1%
#284
0%
#285
1%
#286
0%
#287
1%
#288
0%
#289
1%
#290
0%
#291
1%
#292
0%
#293
1%
#294
0%
#295
1%
#296
0%
#297
1%
#298
0%
#299
1%
#300
0%
#301
1%
#302
1$
0%
#303
1%
b00000000000000000000000000000000 (
#304
0$
0%
b00000000 &
b00000000000000000000000000000000 '
b00000000000000000000000000000001 (
#305
1%
b00000000000000000000000000000000 (
#306
0%
#307
1%
#308
0%
#309
1%
#310
0%
#311
1%
#312
0%
#313
1%
#314
0%
#315
1%
#316
0%
#317
1%
#318
0%
#319
1%
#320
0%
#321
1%
#322
0%
#323
1%
#324
0%
#325
1%
#326
0%
#327
1%
#328
0%
#329
1%
#330
1$
0%
#331
1%
b00000000000000000000000000000001 (
#332
0$
0%
b00000001 &
b00000000000000000000000000000001 '
b00000000000000000000000000000010 (
#333
1%
b00000000000000000000000000000001 (
#334
0%
#335
1%
#336
0%
#337
1%
#338
0%
#339
1%
#340
0%
#341
1%
#342
0%
#343
1%
#344
0%
#345
1%
#346
0%
#347
1%
#348
0%
#349
1%
#350
0%
#351
1%
#352
0%
#353
1%
#354
0%
#355
1%
#356
0%
#357
1%
#358
0%
#359
1%
#360
0%
#361
1%
#362
0%
#363
1%
#364
0%
#365
1%
#366
1$
0%
#367
1%
b00000000000000000000000000000010 (
#368
0$
0%
b00000011 &
b00000000000000000000000000000010 '
b00000000000000000000000000000011 (
#369
1%
b00000000000000000000000000000010 (
#370
0%
#371
1%
#372
0%
#373
1%
#374
0%
#375
1%
#376
0%
#377
1%
#378
0%
#379
1%
#380
0%
#381
1%
#382
0%
#383
1%
#384
0%
#385
1%
#386
0%
#387
1%
#388
0%
#389
1%
#390
0%
#391
1%
#392
0%
#393
1%
#394
1$
0%
#395
1%
b00000000000000000000000000000011 (
#396
0$
0%
b00000111 &
b00000000000000000000000000000011 '
b00000000000000000000000000000100 (
#397
1%
b00000000000000000000000000000011 (
#398
0%
#399
1%
#400
0%
#401
1%
#402
0%
#403
1%
#404
0%
#405
1%
#406
0%
#407
1%
#408
0%
#409
1%
#410
0%
#411
1%
#412
0%
#413
1%
#414
0%
#415
1%
#416
0%
#417
1%
#418
0%
#419
1%
#420
0%
#421
1%
#422
0%
#423
1%
#424
0%
#425
1%
#426
1$
0%
#427
1%
b00000000000000000000000000000100 (
#428
0$
0%
b00001111 &
b00000000000000000000000000000100 '
b00000000000000000000000000000101 (
#429
1%
b00000000000000000000000000000100 (
#430
0%
#431
1%
#432
0%
#433
1%
#434
0%
#435
1%
#436
0%
#437
1%
#438
0%
#439
1%
#440
0%
#441
1%
#442
0%
#443
1%
#444
0%
#445
1%
#446
1$
0%
#447
1%
b00000000000000000000000000000101 (
#448
0$
0%
b00011111 &
b00000000000000000000000000000101 '
b00000000000000000000000000000110 (
#449
1%
b00000000000000000000000000000101 (
#450
0%
#451
1%
#452
0%
#453
1%
#454
0%
#455
1%
#456
0%
#457
1%
#458
0%
#459
1%
#460
0%
#461
1%
#462
1$
0%
#463
1%
b00000000000000000000000000000110 (
#464
0$
0%
b00111111 &
b00000000000000000000000000000110 '
b00000000000000000000000000000111 (
#465
1%
b00000000000000000000000000000110 (
#466
0%
#467
1%
#468
0%
#469
1%
#470
0%
#471
1%
#472
0%
#473
1%
#474
1$
0%
#475
1%
b00000000000000000000000000000111 (
#476
0$
0%
b01111111 &
b00000000000000000000000000000111 '
b00000000000000000000000000001000 (
#477
1%
b00000000000000000000000000000111 (
#478
0%
#479
1%
#480
0%
#481
1%
#482
0%
#483
1%
#484
0%
#485
1%
#486
1$
0%
#487
1%
b00000000000000000000000000001000 (
#488
0$
0%
b11111111 &
b00000000000000000000000000001000 '
b00000000000000000000000000000000 (
#489
1%
b00000000000000000000000000001000 (
#490
0%
#491
1%
#492
0%
#493
1%
#494
0%
#495
1%
#496
1$
0%
#497
1%
b00000000000000000000000000000000 (
#498
0$
0%
b00000000 &
b00000000000000000000000000000000 '
b00000000000000000000000000000001 (
#499
1%
b00000000000000000000000000000000 (
#500
0%
#501
1%
#502
0%
#503
1%
#504
0%
#505
1%
#506
0%
#507
1%
#508
1$
0%
#509
1%
b00000000000000000000000000000001 (
#510
0$
0%
b00000001 &
b00000000000000000000000000000001 '
b00000000000000000000000000000010 (
#511
1%
b00000000000000000000000000000001 (
#512
0%
#513
1%
#514
0%
#515
1%
#516
1$
0%
#517
1%
b00000000000000000000000000000010 (
#518
0$
0%
b00000011 &
b00000000000000000000000000000010 '
b00000000000000000000000000000011 (
#519
1%
b00000000000000000000000000000010 (
#520
0%
#521
1%
#522
0%
#523
1%
#524
1$
0%
#525
1%
b00000000000000000000000000000011 (
#526
0$
0%
b00000111 &
b00000000000000000000000000000011 '
b00000000000000000000000000000100 (
#527
1%
b00000000000000000000000000000011 (
#528
0%
#529
1%
#530
1$
0%
#531
1%
b00000000000000000000000000000100 (
#532
0$
0%
b00001111 &
b00000000000000000000000000000100 '
b00000000000000000000000000000101 (
#533
1%
b00000000000000000000000000000100 (
#534
0%
#535
1%
#536
0%
#537
1%
#538
1$
0%
#539
1%
b00000000000000000000000000000101 (
#540
0$
0%
b00011111 &
b00000000000000000000000000000101 '
b00000000000000000000000000000110 (
#541
1%
b00000000000000000000000000000101 (
#542
0%
#543
1%
#544
0%
#545
1%
#546
1$
0%
#547
1%
b00000000000000000000000000000110 (
#548
0$
0%
b00111111 &
b00000000000000000000000000000110 '
b00000000000000000000000000000111 (
#549
1%
b00000000000000000000000000000110 (
#550
0%
#551
1%
#552
0%
#553
1%
#554
1$
0%
#555
1%
b00000000000000000000000000000111 (
#556
0$
0%
b01111111 &
b00000000000000000000000000000111 '
b00000000000000000000000000001000 (
#557
1%
b00000000000000000000000000000111 (
#558
0%
#559
1%
#560
0%
#561
1%
#562
1$
0%
#563
1%
b00000000000000000000000000001000 (
#564
0$
0%
b11111111 &
b00000000000000000000000000001000 '
b00000000000000000000000000000000 (
#565
1%
b00000000000000000000000000001000 (
#566
0%
#567
1%
#568
0%
#569
1%
#570
1$
0%
#571
1%
b00000000000000000000000000000000 (
#572
0$
0%
b00000000 &
b00000000000000000000000000000000 '
b00000000000000000000000000000001 (
#573
1%
b00000000000000000000000000000000 (
#574
0%
#575
1%
#576
0%
#577
1%
#578
1$
0%
#579
1%
b00000000000000000000000000000001 (
#580
0$
0%
b00000001 &
b00000000000000000000000000000001 '
b00000000000000000000000000000010 (
#581
1%
b00000000000000000000000000000001 (
#582
0%
#583
1%
#584
0%
#585
1%
#586
1$
0%
#587
1%
b00000000000000000000000000000010 (
#588
0$
0%
b00000011 &
b00000000000000000000000000000010 '
b00000000000000000000000000000011 (
#589
1%
b00000000000000000000000000000010 (
#590
0%
#591
1%
#592
0%
#593
1%
#594
0%
#595
1%
#596
1$
0%
#597
1%
b00000000000000000000000000000011 (
#598
0$
0%
b00000111 &
b00000000000000000000000000000011 '
b00000000000000000000000000000100 (
#599
1%
b00000000000000000000000000000011 (
#600
0%
#601
1%
#602
1$
0%
#603
1%
b00000000000000000000000000000100 (
#604
0$
0%
b00001111 &
b00000000000000000000000000000100 '
b00000000000000000000000000000101 (
#605
1%
b00000000000000000000000000000100 (
#606
0%
#607
1%
#608
0%
#609
1%
#610
0%
#611
1%
#612
0%
#613
1%
#614
0%
#615
1%
#616
0%
#617
1%
#618
1$
0%
#619
1%
b00000000000000000000000000000101 (
#620
0$
0%
b00011111 &
b00000000000000000000000000000101 '
b00000000000000000000000000000110 (
#621
1%
b00000000000000000000000000000101 (
#622
0%
#623
1%
#624
0%
#625
1%
#626
1$
0%
#627
1%
b00000000000000000000000000000110 (
#628
0$
0%
b00111111 &
b00000000000000000000000000000110 '
b00000000000000000000000000000111 (
#629
1%
b00000000000000000000000000000110 (
#630
0%
#631
1%
#632
0%
#633
1%
#634
1$
0%
#635
1%
b00000000000000000000000000000111 (
#636
0$
0%
b01111111 &
b00000000000000000000000000000111 '
b00000000000000000000000000001000 (
#637
1%
b00000000000000000000000000000111 (
#638
0%
#639
1%
#640
0%
#641
1%
#642
1$
0%
#643
1%
b00000000000000000000000000001000 (
#644
0$
0%
b11111111 &
b00000000000000000000000000001000 '
b00000000000000000000000000000000 (
#645
1%
b00000000000000000000000000001000 (
#646
0%
#647
1%
#648
0%
#649
1%
#650
1$
0%
#651
1%
b00000000000000000000000000000000 (
#652
0$
0%
b00000000 &
b00000000000000000000000000000000 '
b00000000000000000000000000000001 (
#653
1%
b00000000000000000000000000000000 (
#654
0%
#655
1%
#656
0%
#657
1%
#658
1$
0%
#659
1%
b00000000000000000000000000000001 (
#660
0$
0%
b00000001 &
b00000000000000000000000000000001 '
b00000000000000000000000000000010 (
#661
1%
b00000000000000000000000000000001 (
